samplr/__init__.py
samplr/errors.py
samplr/samplr.py
samplr/strings.py
test/__init__.py
test/test_samplr.py
samplr-1.0.0.dist-info/LICENSE
samplr-1.0.0.dist-info/METADATA
samplr-1.0.0.dist-info/WHEEL
samplr-1.0.0.dist-info/top_level.txt
samplr-1.0.0.dist-info/RECORD
