Metadata-Version: 2.1
Name: samplr
Version: 1.0.0
Summary: A simple decorator for returning a small sample of items from a list.
Home-page: https://github.com/roshaka/samplr
Author: ROSHAKA
Author-email: dan@roshaka.io
Classifier: Programming Language :: Python :: 3
Classifier: License :: OSI Approved :: MIT License
Classifier: Operating System :: OS Independent
Requires-Python: >=3.6
License-File: LICENSE
